wroclaw_taxonomy/Dendrite.py
wroclaw_taxonomy/Plotter.py
wroclaw_taxonomy/__init__.py
wroclawtaxonomy-0.1.1.dist-info/METADATA
wroclawtaxonomy-0.1.1.dist-info/WHEEL
wroclawtaxonomy-0.1.1.dist-info/top_level.txt
wroclawtaxonomy-0.1.1.dist-info/RECORD
