Metadata-Version: 2.1
Name: wroclawtaxonomy
Version: 0.1.1
Summary: Function for creating dendrite using Wroclaw taxonomy
Author-email: Tomasz Matuszek <tom.mateuszek@gmail.com>
Project-URL: Homepage, https://github.com/TomekMatuszek/wroclaw_taxonomy
Project-URL: Bug Reports, https://github.com/TomekMatuszek/wroclaw_taxonomy/issues
Requires-Dist: numpy
Requires-Dist: shapely
Requires-Dist: scipy
Requires-Dist: pandas
Requires-Dist: fiona
Requires-Dist: pyproj
Requires-Dist: geopandas
Requires-Dist: matplotlib
Requires-Dist: imageio
